fluffycow
