Metadata-Version: 1.2
Name: fluffycow
Version: 0.0.5
Summary: A domain-specific language for generating random inputs
Home-page: https://github.com/ChrisTimperley/fluffycow
Author: Chris Timperley
Author-email: ctimperley@cmu.edu
License: Apache License 2.0
Keywords: random,fuzzing,dsl
Platform: UNKNOWN
Classifier: Intended Audience :: Developers
Classifier: Natural Language :: English
Classifier: Programming Language :: Python
Classifier: Programming Language :: Python :: 3
Classifier: Programming Language :: Python :: 3.5
Classifier: Programming Language :: Python :: 3.6
Classifier: Programming Language :: Python :: 3.7
Requires-Python: >=3.5
